freakrandomizer/FreakRandomizer.py
freakrandomizer/__init__.py
freakrandomizer-0.2.2.dist-info/METADATA
freakrandomizer-0.2.2.dist-info/WHEEL
freakrandomizer-0.2.2.dist-info/top_level.txt
freakrandomizer-0.2.2.dist-info/RECORD
