Metadata-Version: 2.4
Name: freakrandomizer
Version: 0.2.2
Summary: FreakRandomizer: This lib is uses a new algorithm and works better than random lib
Home-page: https://github.com/Kutay1062/FreakRandomizer
Author: Kutay
Author-email: Kutay <teknoaioffical@gmail.com>
License: MIT
Project-URL: Homepage, https://github.com/Kutay1062/FreakRandomizer
Project-URL: Repository, https://github.com/Kutay1062/FreakRandomizer
Requires-Python: >=3.8
